lict/__init__.py
lict/core.py
lict-0.2.1.dist-info/LICENSE
lict-0.2.1.dist-info/METADATA
lict-0.2.1.dist-info/WHEEL
lict-0.2.1.dist-info/top_level.txt
lict-0.2.1.dist-info/RECORD
